<annotation>
	<folder>images</folder>
	<filename>66.jpg</filename>
	<path>/Users/tuanperera/Documents/machine_learning_stuff/garbage_detector/raccoon_dataset/images/66.jpg</path>
	<source>
		<database>Unknown</database>
	</source>
	<size>
		<width>162</width>
		<height>311</height>
		<depth>3</depth>
	</size>
	<segmented>0</segmented>
	<object>
		<name>can</name>
		<pose>Unspecified</pose>
		<truncated>0</truncated>
		<difficult>0</difficult>
		<bndbox>
			<xmin>83</xmin>
			<ymin>166</ymin>
			<xmax>149</xmax>
			<ymax>290</ymax>
		</bndbox>
	</object>
</annotation>
