<annotation>
	<folder>bottles</folder>
	<filename>bottle_28.jpg</filename>
	<path>/Users/flintlouis/Desktop/Renewed_dataset/bottles/bottle_85.jpg</path>
	<source>
		<database>Unknown</database>
	</source>
	<size>
		<width>512</width>
		<height>384</height>
		<depth>3</depth>
	</size>
	<segmented>0</segmented>
	<object>
		<name>bottle</name>
		<pose>Unspecified</pose>
		<truncated>0</truncated>
		<difficult>0</difficult>
		<bndbox>
			<xmin>70</xmin>
			<ymin>145</ymin>
			<xmax>291</xmax>
			<ymax>224</ymax>
		</bndbox>
	</object>
</annotation>