<annotation>
	<folder></folder>
	<filename>can-148_jpg.rf.4bb9209732ebd4a3e3ff2b21f73abfe0.jpg</filename>
	<path>can-148_jpg.rf.4bb9209732ebd4a3e3ff2b21f73abfe0.jpg</path>
	<source>
		<database>roboflow.ai</database>
	</source>
	<size>
		<width>300</width>
		<height>300</height>
		<depth>3</depth>
	</size>
	<segmented>0</segmented>
	<object>
		<name>Can</name>
		<pose>Unspecified</pose>
		<truncated>0</truncated>
		<difficult>0</difficult>
		<bndbox>
			<xmin>26</xmin>
			<xmax>120</xmax>
			<ymin>62</ymin>
			<ymax>216</ymax>
		</bndbox>
	</object>
</annotation>
