<annotation>
	<folder></folder>
	<filename>coffee-3811684_640_jpg.rf.6615db558ad8d3e0a4595315e8a27e8f.jpg</filename>
	<path>coffee-3811684_640_jpg.rf.6615db558ad8d3e0a4595315e8a27e8f.jpg</path>
	<source>
		<database>roboflow.ai</database>
	</source>
	<size>
		<width>300</width>
		<height>300</height>
		<depth>3</depth>
	</size>
	<segmented>0</segmented>
	<object>
		<name>Cup</name>
		<pose>Unspecified</pose>
		<truncated>0</truncated>
		<difficult>0</difficult>
		<bndbox>
			<xmin>130</xmin>
			<ymin>48</ymin>
			<xmax>270</xmax>
			<ymax>118</ymax>
		</bndbox>
	</object>
	<object>
		<name>Cup</name>
		<pose>Unspecified</pose>
		<truncated>0</truncated>
		<difficult>0</difficult>
		<bndbox>
			<xmin>116</xmin>
			<ymin>100</ymin>
			<xmax>234</xmax>
			<ymax>158</ymax>
		</bndbox>
	</object>
	<object>
		<name>Cup</name>
		<pose>Unspecified</pose>
		<truncated>0</truncated>
		<difficult>0</difficult>
		<bndbox>
			<xmin>103</xmin>
			<ymin>53</ymin>
			<xmax>129</xmax>
			<ymax>105</ymax>
		</bndbox>
	</object>
</annotation>
