<annotation>
	<folder></folder>
	<filename>cup-45_jpg.rf.0cb56788983d8affeb752da6b9549da2.jpg</filename>
	<path>cup-45_jpg.rf.0cb56788983d8affeb752da6b9549da2.jpg</path>
	<source>
		<database>roboflow.ai</database>
	</source>
	<size>
		<width>300</width>
		<height>300</height>
		<depth>3</depth>
	</size>
	<segmented>0</segmented>
	<object>
		<name>Cup</name>
		<pose>Unspecified</pose>
		<truncated>0</truncated>
		<difficult>0</difficult>
		<bndbox>
			<xmin>39</xmin>
			<ymin>75</ymin>
			<xmax>185</xmax>
			<ymax>249</ymax>
		</bndbox>
	</object>
</annotation>
