<annotation>
	<folder></folder>
	<filename>cup-106_jpg.rf.1835d01ff48668a4a476cb0e70ea6019.jpg</filename>
	<path>cup-106_jpg.rf.1835d01ff48668a4a476cb0e70ea6019.jpg</path>
	<source>
		<database>roboflow.ai</database>
	</source>
	<size>
		<width>300</width>
		<height>300</height>
		<depth>3</depth>
	</size>
	<segmented>0</segmented>
	<object>
		<name>Cup</name>
		<pose>Unspecified</pose>
		<truncated>0</truncated>
		<difficult>0</difficult>
		<bndbox>
			<ymin>102</ymin>
			<xmin>45</xmin>
			<ymax>217</ymax>
			<xmax>202</xmax>
		</bndbox>
	</object>
</annotation>
