<annotation>
	<folder></folder>
	<filename>cup-169_jpg.rf.c1f6e4765fe6249cf2e16e66bdd7e135.jpg</filename>
	<path>cup-169_jpg.rf.c1f6e4765fe6249cf2e16e66bdd7e135.jpg</path>
	<source>
		<database>roboflow.ai</database>
	</source>
	<size>
		<width>300</width>
		<height>300</height>
		<depth>3</depth>
	</size>
	<segmented>0</segmented>
	<object>
		<name>Cup</name>
		<pose>Unspecified</pose>
		<truncated>0</truncated>
		<difficult>0</difficult>
		<bndbox>
			<ymin>31</ymin>
			<xmin>78</xmin>
			<ymax>231</ymax>
			<xmax>205</xmax>
		</bndbox>
	</object>
</annotation>
