<annotation>
  <folder>images</folder>
  <filename>cup_71.jpg</filename>
  <path>images</path>
  <source>
    <database>Unknown</database>
  </source>
  <size>
    <width>3840</width>
    <height>5120</height>
    <depth>3</depth>
  </size>
  <segmented>0</segmented>
  <object>
    <name>can</name>
    <pose>Unspecified</pose>
    <truncated>0</truncated>
    <difficult>0</difficult>
    <bndbox>
      <xmin>257</xmin>
      <ymin>1870</ymin>
      <xmax>1364</xmax>
      <ymax>3915</ymax>
    </bndbox>
  </object>
  <object>
    <name>cup</name>
    <pose>Unspecified</pose>
    <truncated>0</truncated>
    <difficult>0</difficult>
    <bndbox>
      <xmin>1369</xmin>
      <ymin>3032</ymin>
      <xmax>2719</xmax>
      <ymax>4221</ymax>
    </bndbox>
  </object>
  <object>
    <name>cup</name>
    <pose>Unspecified</pose>
    <truncated>0</truncated>
    <difficult>0</difficult>
    <bndbox>
      <xmin>1219</xmin>
      <ymin>1493</ymin>
      <xmax>2753</xmax>
      <ymax>2620</ymax>
    </bndbox>
  </object>
  <object>
    <name>can</name>
    <pose>Unspecified</pose>
    <truncated>0</truncated>
    <difficult>0</difficult>
    <bndbox>
      <xmin>3302</xmin>
      <ymin>1798</ymin>
      <xmax>3840</xmax>
      <ymax>2727</ymax>
    </bndbox>
  </object>
  <object>
    <name>cup</name>
    <pose>Unspecified</pose>
    <truncated>0</truncated>
    <difficult>0</difficult>
    <bndbox>
      <xmin>3068</xmin>
      <ymin>2764</ymin>
      <xmax>3839</xmax>
      <ymax>3500</ymax>
    </bndbox>
  </object>
</annotation>
