<annotation>
	<folder></folder>
	<filename>IMG_20200916_134908_mod_jpg.rf.210be72cadacbff6b0821e4bc28799fd.jpg</filename>
	<path>IMG_20200916_134908_mod_jpg.rf.210be72cadacbff6b0821e4bc28799fd.jpg</path>
	<source>
		<database>roboflow.ai</database>
	</source>
	<size>
		<width>300</width>
		<height>300</height>
		<depth>3</depth>
	</size>
	<segmented>0</segmented>
	<object>
		<name>Cup</name>
		<pose>Unspecified</pose>
		<truncated>0</truncated>
		<difficult>0</difficult>
		<bndbox>
			<xmin>127</xmin>
			<ymin>156</ymin>
			<xmax>241</xmax>
			<ymax>266</ymax>
		</bndbox>
	</object>
</annotation>
