<annotation>
	<folder></folder>
	<filename>IMG_20200916_135023_mod_jpg.rf.17728e0401dacc96b5facf4476ea4d60.jpg</filename>
	<path>IMG_20200916_135023_mod_jpg.rf.17728e0401dacc96b5facf4476ea4d60.jpg</path>
	<source>
		<database>roboflow.ai</database>
	</source>
	<size>
		<width>300</width>
		<height>300</height>
		<depth>3</depth>
	</size>
	<segmented>0</segmented>
	<object>
		<name>Plastic-bottle</name>
		<pose>Unspecified</pose>
		<truncated>0</truncated>
		<difficult>0</difficult>
		<bndbox>
			<xmin>100</xmin>
			<xmax>180</xmax>
			<ymin>67</ymin>
			<ymax>227</ymax>
		</bndbox>
	</object>
</annotation>
