<annotation>
	<folder></folder>
	<filename>IMG_20200926_115002_jpg.rf.8289953cc076d1d3c93532799705b355.jpg</filename>
	<path>IMG_20200926_115002_jpg.rf.8289953cc076d1d3c93532799705b355.jpg</path>
	<source>
		<database>roboflow.ai</database>
	</source>
	<size>
		<width>300</width>
		<height>300</height>
		<depth>3</depth>
	</size>
	<segmented>0</segmented>
	<object>
		<name>Can</name>
		<pose>Unspecified</pose>
		<truncated>0</truncated>
		<difficult>0</difficult>
		<bndbox>
			<xmin>37</xmin>
			<ymin>84</ymin>
			<xmax>135</xmax>
			<ymax>182</ymax>
		</bndbox>
	</object>
</annotation>
