<annotation>
	<folder></folder>
	<filename>IMG_20200916_133505_mod_jpg.rf.f1ab181228332af3fe6eae0f8df37779.jpg</filename>
	<path>IMG_20200916_133505_mod_jpg.rf.f1ab181228332af3fe6eae0f8df37779.jpg</path>
	<source>
		<database>roboflow.ai</database>
	</source>
	<size>
		<width>300</width>
		<height>300</height>
		<depth>3</depth>
	</size>
	<segmented>0</segmented>
	<object>
		<name>Cup</name>
		<pose>Unspecified</pose>
		<truncated>0</truncated>
		<difficult>0</difficult>
		<occluded>0</occluded>
		<bndbox>
			<xmin>130</xmin>
			<xmax>238</xmax>
			<ymin>87</ymin>
			<ymax>228</ymax>
		</bndbox>
	</object>
</annotation>
