<annotation>
	<folder></folder>
	<filename>IMG_20200916_134909_mod_jpg.rf.5680b66500b3ee00df38fc03c14636d5.jpg</filename>
	<path>IMG_20200916_134909_mod_jpg.rf.5680b66500b3ee00df38fc03c14636d5.jpg</path>
	<source>
		<database>roboflow.ai</database>
	</source>
	<size>
		<width>300</width>
		<height>300</height>
		<depth>3</depth>
	</size>
	<segmented>0</segmented>
	<object>
		<name>Cup</name>
		<pose>Unspecified</pose>
		<truncated>0</truncated>
		<difficult>0</difficult>
		<bndbox>
			<xmin>106</xmin>
			<ymin>116</ymin>
			<xmax>150</xmax>
			<ymax>162</ymax>
		</bndbox>
	</object>
</annotation>
