<annotation>
	<folder></folder>
	<filename>IMG_20200916_191319_mod_jpg.rf.c3d09a7afa16300ce3988582a9963287.jpg</filename>
	<path>IMG_20200916_191319_mod_jpg.rf.c3d09a7afa16300ce3988582a9963287.jpg</path>
	<source>
		<database>roboflow.ai</database>
	</source>
	<size>
		<width>300</width>
		<height>300</height>
		<depth>3</depth>
	</size>
	<segmented>0</segmented>
	<object>
		<name>Cup</name>
		<pose>Unspecified</pose>
		<truncated>0</truncated>
		<difficult>0</difficult>
		<bndbox>
			<xmin>187</xmin>
			<ymin>127</ymin>
			<xmax>243</xmax>
			<ymax>207</ymax>
		</bndbox>
	</object>
</annotation>
