<annotation>
	<folder></folder>
	<filename>l,ooom_jpg.rf.c107822ec5ab9c0e8c298e2b3d64cb3f.jpg</filename>
	<path>l,ooom_jpg.rf.c107822ec5ab9c0e8c298e2b3d64cb3f.jpg</path>
	<source>
		<database>roboflow.ai</database>
	</source>
	<size>
		<width>300</width>
		<height>300</height>
		<depth>3</depth>
	</size>
	<segmented>0</segmented>
	<object>
		<name>Can</name>
		<pose>Unspecified</pose>
		<truncated>0</truncated>
		<difficult>0</difficult>
		<bndbox>
			<xmin>109</xmin>
			<ymin>184</ymin>
			<xmax>234</xmax>
			<ymax>230</ymax>
		</bndbox>
	</object>
	<object>
		<name>Can</name>
		<pose>Unspecified</pose>
		<truncated>0</truncated>
		<difficult>0</difficult>
		<bndbox>
			<xmin>126</xmin>
			<ymin>73</ymin>
			<xmax>213</xmax>
			<ymax>154</ymax>
		</bndbox>
	</object>
	<object>
		<name>Can</name>
		<pose>Unspecified</pose>
		<truncated>0</truncated>
		<difficult>0</difficult>
		<bndbox>
			<xmin>223</xmin>
			<ymin>117</ymin>
			<xmax>273</xmax>
			<ymax>175</ymax>
		</bndbox>
	</object>
	<object>
		<name>Can</name>
		<pose>Unspecified</pose>
		<truncated>0</truncated>
		<difficult>0</difficult>
		<bndbox>
			<xmin>92</xmin>
			<ymin>110</ymin>
			<xmax>147</xmax>
			<ymax>186</ymax>
		</bndbox>
	</object>
</annotation>
