<annotation>
	<folder></folder>
	<filename>metal3can_jpg.rf.ba03e3b309c367d663930bda52c261a9.jpg</filename>
	<path>metal3can_jpg.rf.ba03e3b309c367d663930bda52c261a9.jpg</path>
	<source>
		<database>roboflow.ai</database>
	</source>
	<size>
		<width>300</width>
		<height>300</height>
		<depth>3</depth>
	</size>
	<segmented>0</segmented>
	<object>
		<name>Can</name>
		<pose>Unspecified</pose>
		<truncated>0</truncated>
		<difficult>0</difficult>
		<bndbox>
			<xmin>60</xmin>
			<ymin>75</ymin>
			<xmax>170</xmax>
			<ymax>173</ymax>
		</bndbox>
	</object>
</annotation>
