<annotation>
	<folder></folder>
	<filename>mix-64_jpg.rf.2455a25e44268cd386bc60270430eb95.jpg</filename>
	<path>mix-64_jpg.rf.2455a25e44268cd386bc60270430eb95.jpg</path>
	<source>
		<database>roboflow.ai</database>
	</source>
	<size>
		<width>300</width>
		<height>300</height>
		<depth>3</depth>
	</size>
	<segmented>0</segmented>
	<object>
		<name>Cup</name>
		<pose>Unspecified</pose>
		<truncated>0</truncated>
		<difficult>0</difficult>
		<bndbox>
			<xmin>104</xmin>
			<xmax>189</xmax>
			<ymin>143</ymin>
			<ymax>235</ymax>
		</bndbox>
	</object>
	<object>
		<name>Plastic-bottle</name>
		<pose>Unspecified</pose>
		<truncated>0</truncated>
		<difficult>0</difficult>
		<bndbox>
			<xmin>196</xmin>
			<xmax>231</xmax>
			<ymin>65</ymin>
			<ymax>143</ymax>
		</bndbox>
	</object>
	<object>
		<name>Cup</name>
		<pose>Unspecified</pose>
		<truncated>0</truncated>
		<difficult>0</difficult>
		<bndbox>
			<xmin>228</xmin>
			<xmax>252</xmax>
			<ymin>99</ymin>
			<ymax>123</ymax>
		</bndbox>
	</object>
</annotation>
