<annotation>
	<folder></folder>
	<filename>mix-19_jpg.rf.05ce33cdc230d6c40e4c623f993c24e6.jpg</filename>
	<path>mix-19_jpg.rf.05ce33cdc230d6c40e4c623f993c24e6.jpg</path>
	<source>
		<database>roboflow.ai</database>
	</source>
	<size>
		<width>300</width>
		<height>300</height>
		<depth>3</depth>
	</size>
	<segmented>0</segmented>
	<object>
		<name>Plastic-bottle</name>
		<pose>Unspecified</pose>
		<truncated>0</truncated>
		<difficult>0</difficult>
		<bndbox>
			<xmin>108</xmin>
			<xmax>147</xmax>
			<ymin>66</ymin>
			<ymax>216</ymax>
		</bndbox>
	</object>
	<object>
		<name>Cup</name>
		<pose>Unspecified</pose>
		<truncated>0</truncated>
		<difficult>0</difficult>
		<bndbox>
			<xmin>61</xmin>
			<xmax>98</xmax>
			<ymin>149</ymin>
			<ymax>219</ymax>
		</bndbox>
	</object>
	<object>
		<name>Cup</name>
		<pose>Unspecified</pose>
		<truncated>0</truncated>
		<difficult>0</difficult>
		<bndbox>
			<xmin>148</xmin>
			<xmax>179</xmax>
			<ymin>131</ymin>
			<ymax>192</ymax>
		</bndbox>
	</object>
	<object>
		<name>Cup</name>
		<pose>Unspecified</pose>
		<truncated>0</truncated>
		<difficult>0</difficult>
		<bndbox>
			<xmin>182</xmin>
			<xmax>212</xmax>
			<ymin>117</ymin>
			<ymax>171</ymax>
		</bndbox>
	</object>
</annotation>
