<annotation>
	<folder></folder>
	<filename>starbuckscup_jpg.rf.a36763a580e2b252e6d381f1cd4d7f99.jpg</filename>
	<path>starbuckscup_jpg.rf.a36763a580e2b252e6d381f1cd4d7f99.jpg</path>
	<source>
		<database>roboflow.ai</database>
	</source>
	<size>
		<width>300</width>
		<height>300</height>
		<depth>3</depth>
	</size>
	<segmented>0</segmented>
	<object>
		<name>Cup</name>
		<pose>Unspecified</pose>
		<truncated>0</truncated>
		<difficult>0</difficult>
		<bndbox>
			<xmin>36</xmin>
			<ymin>90</ymin>
			<xmax>235</xmax>
			<ymax>222</ymax>
		</bndbox>
	</object>
</annotation>
