<annotation>
	<folder></folder>
	<filename>trash24_jpg.rf.80973e1ddecb48e1dc7d2616fbc956c0.jpg</filename>
	<path>trash24_jpg.rf.80973e1ddecb48e1dc7d2616fbc956c0.jpg</path>
	<source>
		<database>roboflow.ai</database>
	</source>
	<size>
		<width>300</width>
		<height>300</height>
		<depth>3</depth>
	</size>
	<segmented>0</segmented>
	<object>
		<name>Trash</name>
		<pose>Unspecified</pose>
		<truncated>0</truncated>
		<difficult>0</difficult>
		<bndbox>
			<xmin>2</xmin>
			<ymin>82</ymin>
			<xmax>288</xmax>
			<ymax>292</ymax>
		</bndbox>
	</object>
</annotation>
