<annotation>
	<folder></folder>
	<filename>trash-102_jpg.rf.d0150c7007cad62cf4148220b320303b.jpg</filename>
	<path>trash-102_jpg.rf.d0150c7007cad62cf4148220b320303b.jpg</path>
	<source>
		<database>roboflow.ai</database>
	</source>
	<size>
		<width>300</width>
		<height>300</height>
		<depth>3</depth>
	</size>
	<segmented>0</segmented>
	<object>
		<name>Trash</name>
		<pose>Unspecified</pose>
		<truncated>0</truncated>
		<difficult>0</difficult>
		<bndbox>
			<xmin>51</xmin>
			<ymin>103</ymin>
			<xmax>173</xmax>
			<ymax>255</ymax>
		</bndbox>
	</object>
</annotation>
