<annotation>
	<folder></folder>
	<filename>trash-68_jpg.rf.37732b17cf8d86e53ec52449fe2450de.jpg</filename>
	<path>trash-68_jpg.rf.37732b17cf8d86e53ec52449fe2450de.jpg</path>
	<source>
		<database>roboflow.ai</database>
	</source>
	<size>
		<width>300</width>
		<height>300</height>
		<depth>3</depth>
	</size>
	<segmented>0</segmented>
	<object>
		<name>Trash</name>
		<pose>Unspecified</pose>
		<truncated>0</truncated>
		<difficult>0</difficult>
		<bndbox>
			<xmin>96</xmin>
			<xmax>249</xmax>
			<ymin>32</ymin>
			<ymax>275</ymax>
		</bndbox>
	</object>
</annotation>
