<annotation>
	<folder></folder>
	<filename>trash49_jpg.rf.4f3bd0363a688094c469e309da53f770.jpg</filename>
	<path>trash49_jpg.rf.4f3bd0363a688094c469e309da53f770.jpg</path>
	<source>
		<database>roboflow.ai</database>
	</source>
	<size>
		<width>300</width>
		<height>300</height>
		<depth>3</depth>
	</size>
	<segmented>0</segmented>
	<object>
		<name>Trash</name>
		<pose>Unspecified</pose>
		<truncated>0</truncated>
		<difficult>0</difficult>
		<occluded>0</occluded>
		<bndbox>
			<xmin>91</xmin>
			<xmax>252</xmax>
			<ymin>44</ymin>
			<ymax>286</ymax>
		</bndbox>
	</object>
</annotation>
